LICENSE
README.md
pyproject.toml
src/axolotl_plugin_atropos.egg-info/PKG-INFO
src/axolotl_plugin_atropos.egg-info/SOURCES.txt
src/axolotl_plugin_atropos.egg-info/dependency_links.txt
src/axolotl_plugin_atropos.egg-info/requires.txt
src/axolotl_plugin_atropos.egg-info/top_level.txt
src/plugin_atropos/__init__.py
src/plugin_atropos/args.py
src/plugin_atropos/datasets.py
src/plugin_atropos/plugin.py
src/plugin_atropos/vllm_serve.py
src/plugin_atropos/server_handling/__init__.py
src/plugin_atropos/trainers/__init__.py
src/plugin_atropos/trainers/grpo.py