Metadata-Version: 2.4
Name: axolotl-plugin-atropos
Version: 0.0.2
Summary: Axolotl Plugin integrating Nous Research's Atropos for RL
Author: Wing Lian
License:                                  Apache License
Classifier: Programming Language :: Python :: 3
License-File: LICENSE
Requires-Dist: torch==2.6.0
Requires-Dist: axolotl>=0.9.2
Requires-Dist: requests
Requires-Dist: trl==0.17.0
Requires-Dist: vllm==0.8.5.post1
Dynamic: license-file
